asgi_ws/__init__.py
asgi_ws/static/js/websockets.js
asgi_ws/websockets.py
asgi_ws-1.0.0.dist-info/METADATA
asgi_ws-1.0.0.dist-info/WHEEL
asgi_ws-1.0.0.dist-info/RECORD
