Metadata-Version: 2.1
Name: asgi_ws
Version: 1.0.0
Summary: 
Author: Gonzalo Ayuso
Author-email: gonzalo123@gmail.com
Requires-Python: >=3.9,<4.0
Classifier: Programming Language :: Python :: 3
Classifier: Programming Language :: Python :: 3.9
Classifier: Programming Language :: Python :: 3.10
Classifier: Programming Language :: Python :: 3.11
Classifier: Programming Language :: Python :: 3.12
Requires-Dist: fastapi (>=0.115.6,<0.116.0)
Requires-Dist: pyjwt (>=2.10.1,<3.0.0)
Requires-Dist: requests (>=2.32.3,<3.0.0)
Requires-Dist: uvicorn (>=0.32.1,<0.33.0)
Requires-Dist: websockets (>=14.1,<15.0)
